hdcc/HDProg.py
hdcc/HDTypes.py
hdcc/__init__.py
hdcc-0.6.4.dist-info/METADATA
hdcc-0.6.4.dist-info/WHEEL
hdcc-0.6.4.dist-info/RECORD
