Metadata-Version: 2.1
Name: hdcc
Version: 0.6.4
Summary: 
Author: Yifan Yang
Author-email: yyang29@stanford.edu
Requires-Python: >=3.8,<4.0
Classifier: Programming Language :: Python :: 3
Classifier: Programming Language :: Python :: 3.8
Classifier: Programming Language :: Python :: 3.9
Classifier: Programming Language :: Python :: 3.10
Classifier: Programming Language :: Python :: 3.11
Requires-Dist: numpy (>=1.19.2)
